MANIFEST.in
README.rst
setup.py
django_smokealarm.egg-info/PKG-INFO
django_smokealarm.egg-info/SOURCES.txt
django_smokealarm.egg-info/dependency_links.txt
django_smokealarm.egg-info/requires.txt
django_smokealarm.egg-info/top_level.txt
smokealarm/__init__.py
smokealarm/admin.py
smokealarm/models.py
smokealarm/tests.py
smokealarm/urls.py
smokealarm/views.py
smokealarm/static/js/smokealarm.js