Metadata-Version: 1.1
Name: django-smokealarm
Version: 2013.05.13.0
Summary: Simple JavaScript error reporting.
Home-page: https://github.com/bradbeattie/django-smokealarm
Author: Brad Beattie
Author-email: bradbeattie@gmail.com
License: BSD
Platform: UNKNOWN
Classifier: Development Status :: 4 - Beta
Classifier: Environment :: Web Environment
Classifier: Framework :: Django
Classifier: Intended Audience :: Developers
Classifier: License :: OSI Approved :: BSD License
Classifier: Operating System :: OS Independent
Classifier: Programming Language :: Python
Classifier: Topic :: Software Development :: Libraries :: Python Modules
